snakesay/__init__.py
snakesay/snakesay.py
snakesay-0.10.1.dist-info/LICENSE
snakesay-0.10.1.dist-info/METADATA
snakesay-0.10.1.dist-info/WHEEL
snakesay-0.10.1.dist-info/entry_points.txt
snakesay-0.10.1.dist-info/top_level.txt
snakesay-0.10.1.dist-info/RECORD
