Metadata-Version: 2.1
Name: snakesay
Version: 0.10.1
Summary: speaking snake
Author-email: PythonAnywhere Developers <developers@pythonanywhere.com>
License: MIT
Classifier: Programming Language :: Python :: 3.10
Classifier: Programming Language :: Python :: 3.9
Classifier: Programming Language :: Python :: 3.8
Classifier: Programming Language :: Python :: 3.7
Classifier: Programming Language :: Python :: 3.6
Classifier: License :: OSI Approved :: MIT License
Classifier: Operating System :: OS Independent
Requires-Python: >=3.7
License-File: LICENSE
